{"name":"Meet the Bear","bg":"/story/rb/bg/forestb.png","age":0,"translations":[{"lang":"ru-RU","name":"Встреча с медведем"},{"lang":"vi-VN","name":"Gặp gấu"},{"lang":"zh-CN","name":"遇见熊"},{"lang":"hi-IN","name":"भालू से मुलाकात"},{"lang":"th-TH","name":"พบกับหมี"},{"lang":"tr-TR","name":"Ayı\u0027yla Tanış"},{"lang":"pt-BR","name":"Encontro com o Urso"},{"lang":"de-DE","name":"Triff den Bären"},{"lang":"id-ID","name":"Bertemu Beruang"},{"lang":"fr-FR","name":"Rencontre avec l\u0027ours"}],"items":[{"name":"Meet the Bear","actor":"","dialogType":"Normal","translates":[{"lang":"ru-RU","name":"Встреча с медведем"},{"lang":"vi-VN","name":"Gặp gấu"},{"lang":"zh-CN","name":"遇见熊"},{"lang":"hi-IN","name":"भालू से मुलाकात"},{"lang":"th-TH","name":"พบกับหมี"},{"lang":"tr-TR","name":"Ayı\u0027yla Tanış"},{"lang":"pt-BR","name":"Encontro com o Urso"},{"lang":"de-DE","name":"Triff den Bären"},{"lang":"id-ID","name":"Bertemu Beruang"},{"lang":"fr-FR","name":"Rencontre avec l\u0027ours"}],"actions":[]},{"name":"Roar! Who\u0027s making noise here?","actor":"Bear","dialogType":"Normal","translates":[{"lang":"ru-RU","name":"Ррр! Кто тут шумит?"},{"lang":"vi-VN","name":"Gầm! Ai gây ồn ở đây?"},{"lang":"zh-CN","name":"吼！谁在这儿吵闹？"},{"lang":"hi-IN","name":"गर्जना! यहाँ शोर कौन कर रहा है?"},{"lang":"th-TH","name":"คำราม! ใครมารบกวนที่นี่?"},{"lang":"tr-TR","name":"Kükreme! Burada gürültü yapan kim?"},{"lang":"pt-BR","name":"Rugido! Quem está fazendo barulho aqui?"},{"lang":"de-DE","name":"Brüll! Wer macht hier Lärm?"},{"lang":"id-ID","name":"Mengaum! Siapa yang berisik di sini?"},{"lang":"fr-FR","name":"Grrr! Qui fait du bruit ici?"}],"actions":[]},{"name":"It\u0027s me, Bun! I\u0027m exploring the forest.","actor":"Bun","dialogType":"Normal","translates":[{"lang":"ru-RU","name":"Это я, Бан! Я исследую лес."},{"lang":"vi-VN","name":"Là tôi, Bun! Tôi đang khám phá rừng."},{"lang":"zh-CN","name":"是我，小面包！我在探索森林。"},{"lang":"hi-IN","name":"मैं हूँ, बन! मैं जंगल का पता लगा रहा हूँ।"},{"lang":"th-TH","name":"ฉันเอง บัน! ฉันกำลังสำรวจป่า"},{"lang":"tr-TR","name":"Benim, Bun! Ormanı keşfediyorum."},{"lang":"pt-BR","name":"Sou eu, Bun! Estou explorando a floresta."},{"lang":"de-DE","name":"Ich bin\u0027s, Bun! Ich erkunde den Wald."},{"lang":"id-ID","name":"Ini aku, Bun! Aku sedang menjelajahi hutan."},{"lang":"fr-FR","name":"C\u0027est moi, Bun! J\u0027explore la forêt."}],"actions":[]},{"name":"You are small. I am big!","actor":"Bear","dialogType":"Normal","translates":[{"lang":"ru-RU","name":"Ты маленький. Я большой!"},{"lang":"vi-VN","name":"Ngươi nhỏ bé. Ta to lớn!"},{"lang":"zh-CN","name":"你很小。我很大！"},{"lang":"hi-IN","name":"तुम छोटे हो। मैं बड़ा हूँ!"},{"lang":"th-TH","name":"เจ้าเล็ก ฉันใหญ่!"},{"lang":"tr-TR","name":"Sen küçüksün. Ben büyüğüm!"},{"lang":"pt-BR","name":"Você é pequeno. Eu sou grande!"},{"lang":"de-DE","name":"Du bist klein. Ich bin groß!"},{"lang":"id-ID","name":"Kamu kecil. Aku besar!"},{"lang":"fr-FR","name":"Tu es petit. Je suis grand!"}],"actions":[]},{"name":"I was made of flour and pan. I rolled from Gran, Rabbit, and even the Wolf!","actor":"Bun","dialogType":"Normal","translates":[{"lang":"ru-RU","name":"Я из муки и сковороды. Укатился от бабушки, зайца и даже волка!"},{"lang":"vi-VN","name":"Ta được làm từ bột và chảo. Ta đã lăn khỏi bà, thỏ và cả sói!"},{"lang":"zh-CN","name":"我是用面粉和锅做的。我从奶奶、兔子甚至狼那里滚走了！"},{"lang":"hi-IN","name":"मैं आटे और पैन से बना था। मैं दादी, खरगोश और यहाँ तक कि भेड़िये से लुढ़का!"},{"lang":"th-TH","name":"ฉันทำจากแป้งและกระทะ ฉันกลิ้งจากยาย กระต่าย และแม้แต่หมาป่า!"},{"lang":"tr-TR","name":"Un ve tavadan yapılmıştım. Büyükanneden, tavşandan ve hatta kurttan yuvarlandım!"},{"lang":"pt-BR","name":"Eu fui feito de farinha e panela. Rolei da vovó, do coelho e até do lobo!"},{"lang":"de-DE","name":"Ich war aus Mehl und Pfanne. Ich rollte von Oma, Hase und sogar dem Wolf!"},{"lang":"id-ID","name":"Aku terbuat dari tepung dan wajan. Aku menggelinding dari Nenek, Kelinci, dan bahkan Serigala!"},{"lang":"fr-FR","name":"J\u0027étais fait de farine et de poêle. J\u0027ai roulé de Mémé, du Lapin et même du Loup!"}],"actions":[]},{"name":"Even the Wolf? Hmm… You are brave.","actor":"Bear","dialogType":"Normal","translates":[{"lang":"ru-RU","name":"Даже от Волка? Хм… Ты смелый."},{"lang":"vi-VN","name":"Cả sói luôn? Hmm… Ngươi dũng cảm đấy."},{"lang":"zh-CN","name":"连狼都？嗯…你很勇敢。"},{"lang":"hi-IN","name":"भेड़िए से भी? हम्म… तुम बहादुर हो।"},{"lang":"th-TH","name":"แม้แต่หมาป่า? อืม…เธอกล้าหาญดี"},{"lang":"tr-TR","name":"Kurttan bile mi? Hmm… Cesursun."},{"lang":"pt-BR","name":"Até o lobo? Hmm… Você é corajoso."},{"lang":"de-DE","name":"Sogar der Wolf? Hmm… Du bist mutig."},{"lang":"id-ID","name":"Bahkan serigalanya? Hmm… Kau berani."},{"lang":"fr-FR","name":"Même le loup ? Hmm… Tu es courageux."}],"actions":[]},{"name":"Dot, what can I say?","actor":"Bun","dialogType":"Normal","translates":[{"lang":"ru-RU","name":"Дот, что мне сказать?"},{"lang":"vi-VN","name":"Dot, ta nên nói gì?"},{"lang":"zh-CN","name":"点点，我该说什么？"},{"lang":"hi-IN","name":"डॉट, मैं क्या कहूँ?"},{"lang":"th-TH","name":"ดอท ฉันควรพูดอะไรดี?"},{"lang":"tr-TR","name":"Dot, ne demeliyim?"},{"lang":"pt-BR","name":"Dot, o que devo dizer?"},{"lang":"de-DE","name":"Dot, was soll ich sagen?"},{"lang":"id-ID","name":"Dot, apa yang harus kukatakan?"},{"lang":"fr-FR","name":"Dot, que dois-je dire ?"}],"actions":[{"name":"You are big and strong!","isCorrect":true,"score":1,"translates":[{"lang":"ru-RU","name":"Ты большой и сильный!"},{"lang":"vi-VN","name":"Ngươi to lớn và mạnh mẽ!"},{"lang":"zh-CN","name":"你又大又强壮！"},{"lang":"hi-IN","name":"तुम बड़े और ताकतवर हो!"},{"lang":"th-TH","name":"ท่านใหญ่โตและแข็งแรง!"},{"lang":"tr-TR","name":"Sen büyük ve güçlüsün!"},{"lang":"pt-BR","name":"Você é grande e forte!"},{"lang":"de-DE","name":"Du bist groß und stark!"},{"lang":"id-ID","name":"Kamu besar dan kuat!"},{"lang":"fr-FR","name":"Tu es grand et fort !"}]},{"name":"I am small and weak!","isCorrect":false,"score":0,"translates":[{"lang":"ru-RU","name":"Я маленький и слабый!"},{"lang":"vi-VN","name":"Ta nhỏ bé và yếu ớt!"},{"lang":"zh-CN","name":"我又小又弱！"},{"lang":"hi-IN","name":"मैं छोटा और कमजोर हूँ!"},{"lang":"th-TH","name":"ฉันเล็กและอ่อนแอ!"},{"lang":"tr-TR","name":"Ben küçük ve zayıfım!"},{"lang":"pt-BR","name":"Eu sou pequeno e fraco!"},{"lang":"de-DE","name":"Ich bin klein und schwach!"},{"lang":"id-ID","name":"Aku kecil dan lemah!"},{"lang":"fr-FR","name":"Je suis petit et faible !"}]},{"name":"You are too fat!","isCorrect":false,"score":0,"translates":[{"lang":"ru-RU","name":"Ты слишком толстый!"},{"lang":"vi-VN","name":"Ngươi quá béo!"},{"lang":"zh-CN","name":"你太胖了！"},{"lang":"hi-IN","name":"तुम बहुत मोटे हो!"},{"lang":"th-TH","name":"ท่านอ้วนเกินไป!"},{"lang":"tr-TR","name":"Sen çok şişmansın!"},{"lang":"pt-BR","name":"Você é muito gordo!"},{"lang":"de-DE","name":"Du bist zu fett!"},{"lang":"id-ID","name":"Kamu terlalu gemuk!"},{"lang":"fr-FR","name":"Tu es trop gros !"}]}]},{"name":"Haha! That\u0027s nice. I like that.","actor":"Bear","dialogType":"Normal","translates":[{"lang":"ru-RU","name":"Ха-ха! Приятно. Мне нравится."},{"lang":"vi-VN","name":"Ha ha! Tốt lắm. Ta thích điều đó."},{"lang":"zh-CN","name":"哈哈！很好。我喜欢。"},{"lang":"hi-IN","name":"हाहा! अच्छा है। मुझे यह पसंद है।"},{"lang":"th-TH","name":"ฮ่าๆ! ดีมาก ฉันชอบ"},{"lang":"tr-TR","name":"Haha! Güzel. Bunu beğendim."},{"lang":"pt-BR","name":"Haha! Legal. Gostei disso."},{"lang":"de-DE","name":"Haha! Das ist nett. Das gefällt mir."},{"lang":"id-ID","name":"Haha! Bagus. Aku suka itu."},{"lang":"fr-FR","name":"Haha ! Sympa. J\u0027aime ça."}],"actions":[]},{"name":"You can go, little Bun.","actor":"Bear","dialogType":"Normal","translates":[{"lang":"ru-RU","name":"Можешь идти, маленький Бан."},{"lang":"vi-VN","name":"Ngươi có thể đi, Bun nhỏ."},{"lang":"zh-CN","name":"你可以走了，小面包。"},{"lang":"hi-IN","name":"तुम जा सकते हो, छोटे बन।"},{"lang":"th-TH","name":"เจ้าไปได้แล้ว บันน้อย"},{"lang":"tr-TR","name":"Gidebilirsin, küçük Bun."},{"lang":"pt-BR","name":"Pode ir, pequeno Bun."},{"lang":"de-DE","name":"Du kannst gehen, kleines Bun."},{"lang":"id-ID","name":"Kau boleh pergi, Bun kecil."},{"lang":"fr-FR","name":"Tu peux y aller, petit Bun."}],"actions":[]},{"name":"Bye, Bear!","actor":"Bun","dialogType":"Normal","translates":[{"lang":"ru-RU","name":"Пока, Медведь!"},{"lang":"vi-VN","name":"Tạm biệt, gấu!"},{"lang":"zh-CN","name":"再见，熊！"},{"lang":"hi-IN","name":"अलविदा, भालू!"},{"lang":"th-TH","name":"ลาก่อนหมี!"},{"lang":"tr-TR","name":"Güle güle, ayı!"},{"lang":"pt-BR","name":"Tchau, urso!"},{"lang":"de-DE","name":"Tschüss, Bär!"},{"lang":"id-ID","name":"Sampai jumpa, Beruang!"},{"lang":"fr-FR","name":"Au revoir, Ours !"}],"actions":[]},{"name":"What did Bun say?","actor":"Dot","dialogType":"Normal","translates":[{"lang":"ru-RU","name":"Что сказал Бан?"},{"lang":"vi-VN","name":"Bun đã nói gì?"},{"lang":"zh-CN","name":"面包说了什么？"},{"lang":"hi-IN","name":"बन ने क्या कहा?"},{"lang":"th-TH","name":"บันพูดว่าอะไร?"},{"lang":"tr-TR","name":"Bun ne dedi?"},{"lang":"pt-BR","name":"O que o Bun disse?"},{"lang":"de-DE","name":"Was hat Bun gesagt?"},{"lang":"id-ID","name":"Apa yang Bun katakan?"},{"lang":"fr-FR","name":"Qu\u0027a dit Bun ?"}],"actions":[{"name":"Bye, Bear!","isCorrect":true,"score":1,"translates":[{"lang":"ru-RU","name":"Пока, Медведь!"},{"lang":"vi-VN","name":"Tạm biệt, gấu!"},{"lang":"zh-CN","name":"再见，熊！"},{"lang":"hi-IN","name":"अलविदा, भालू!"},{"lang":"th-TH","name":"ลาก่อนหมี!"},{"lang":"tr-TR","name":"Güle güle, ayı!"},{"lang":"pt-BR","name":"Tchau, urso!"},{"lang":"de-DE","name":"Tschüss, Bär!"},{"lang":"id-ID","name":"Sampai jumpa, Beruang!"},{"lang":"fr-FR","name":"Au revoir, Ours !"}]},{"name":"Hello, Bear!","isCorrect":false,"score":0,"translates":[{"lang":"ru-RU","name":"Привет, Медведь!"},{"lang":"vi-VN","name":"Xin chào, gấu!"},{"lang":"zh-CN","name":"你好，熊！"},{"lang":"hi-IN","name":"नमस्ते, भालू!"},{"lang":"th-TH","name":"สวัสดีหมี!"},{"lang":"tr-TR","name":"Merhaba, ayı!"},{"lang":"pt-BR","name":"Olá, urso!"},{"lang":"de-DE","name":"Hallo, Bär!"},{"lang":"id-ID","name":"Halo, Beruang!"},{"lang":"fr-FR","name":"Bonjour, Ours !"}]},{"name":"Run, Bear!","isCorrect":false,"score":0,"translates":[{"lang":"ru-RU","name":"Беги, Медведь!"},{"lang":"vi-VN","name":"Chạy đi, gấu!"},{"lang":"zh-CN","name":"快跑，熊！"},{"lang":"hi-IN","name":"भागो, भालू!"},{"lang":"th-TH","name":"วิ่งไปหมี!"},{"lang":"tr-TR","name":"Koş, ayı!"},{"lang":"pt-BR","name":"Corra, urso!"},{"lang":"de-DE","name":"Lauf, Bär!"},{"lang":"id-ID","name":"Lari, Beruang!"},{"lang":"fr-FR","name":"Cours, Ours !"}]}]},{"name":"Who is big and strong?","actor":"Dot","dialogType":"Normal","translates":[{"lang":"ru-RU","name":"Кто большой и сильный?"},{"lang":"vi-VN","name":"Ai to lớn và mạnh mẽ?"},{"lang":"zh-CN","name":"谁又大又强壮？"},{"lang":"hi-IN","name":"कौन बड़ा और मजबूत है?"},{"lang":"th-TH","name":"ใครใหญ่และแข็งแรง?"},{"lang":"tr-TR","name":"Kim büyük ve güçlü?"},{"lang":"pt-BR","name":"Quem é grande e forte?"},{"lang":"de-DE","name":"Wer ist groß und stark?"},{"lang":"id-ID","name":"Siapa yang besar dan kuat?"},{"lang":"fr-FR","name":"Qui est grand et fort ?"}],"actions":[{"name":"The Bear","isCorrect":true,"score":1,"translates":[{"lang":"ru-RU","name":"Медведь"},{"lang":"vi-VN","name":"Gấu"},{"lang":"zh-CN","name":"熊"},{"lang":"hi-IN","name":"भालू"},{"lang":"th-TH","name":"หมี"},{"lang":"tr-TR","name":"Ayı"},{"lang":"pt-BR","name":"O urso"},{"lang":"de-DE","name":"Der Bär"},{"lang":"id-ID","name":"Beruang"},{"lang":"fr-FR","name":"L\u0027ours"}]},{"name":"The Bun","isCorrect":false,"score":0,"translates":[{"lang":"ru-RU","name":"Бан"},{"lang":"vi-VN","name":"Bun"},{"lang":"zh-CN","name":"面包"},{"lang":"hi-IN","name":"बन"},{"lang":"th-TH","name":"บัน"},{"lang":"tr-TR","name":"Bun"},{"lang":"pt-BR","name":"O Bun"},{"lang":"de-DE","name":"Das Bun"},{"lang":"id-ID","name":"Bun"},{"lang":"fr-FR","name":"Le Bun"}]},{"name":"The Dot","isCorrect":false,"score":0,"translates":[{"lang":"ru-RU","name":"Дот"},{"lang":"vi-VN","name":"Dot"},{"lang":"zh-CN","name":"点点"},{"lang":"hi-IN","name":"डॉट"},{"lang":"th-TH","name":"ดอท"},{"lang":"tr-TR","name":"Dot"},{"lang":"pt-BR","name":"O Dot"},{"lang":"de-DE","name":"Der Dot"},{"lang":"id-ID","name":"Dot"},{"lang":"fr-FR","name":"Le Dot"}]}]},{"name":"Say: You are big and strong!","actor":"Dot","dialogType":"Normal","translates":[{"lang":"ru-RU","name":"Скажи: Ты большой и сильный!"},{"lang":"vi-VN","name":"Nói: Ngươi to lớn và mạnh mẽ!"},{"lang":"zh-CN","name":"说：你又大又强壮！"},{"lang":"hi-IN","name":"कहो: तुम बड़े और मजबूत हो!"},{"lang":"th-TH","name":"พูดว่า: ท่านใหญ่โตและแข็งแรง!"},{"lang":"tr-TR","name":"De ki: Sen büyük ve güçlüsün!"},{"lang":"pt-BR","name":"Diga: Você é grande e forte!"},{"lang":"de-DE","name":"Sag: Du bist groß und stark!"},{"lang":"id-ID","name":"Katakan: Kamu besar dan kuat!"},{"lang":"fr-FR","name":"Dis : Tu es grand et fort !"}],"actions":[{"name":"You are big and strong!","isCorrect":true,"score":1,"translates":[{"lang":"ru-RU","name":"Ты большой и сильный!"},{"lang":"vi-VN","name":"Ngươi to lớn và mạnh mẽ!"},{"lang":"zh-CN","name":"你又大又强壮！"},{"lang":"hi-IN","name":"तुम बड़े और मजबूत हो!"},{"lang":"th-TH","name":"ท่านใหญ่โตและแข็งแรง!"},{"lang":"tr-TR","name":"Sen büyük ve güçlüsün!"},{"lang":"pt-BR","name":"Você é grande e forte!"},{"lang":"de-DE","name":"Du bist groß und stark!"},{"lang":"id-ID","name":"Kamu besar dan kuat!"},{"lang":"fr-FR","name":"Tu es grand et fort !"}]},{"name":"I am big and strong!","isCorrect":false,"score":0,"translates":[{"lang":"ru-RU","name":"Я большой и сильный!"},{"lang":"vi-VN","name":"Ta to lớn và mạnh mẽ!"},{"lang":"zh-CN","name":"我又大又强壮！"},{"lang":"hi-IN","name":"मैं बड़ा और मजबूत हूँ!"},{"lang":"th-TH","name":"ฉันใหญ่และแข็งแรง!"},{"lang":"tr-TR","name":"Ben büyük ve güçlüyüm!"},{"lang":"pt-BR","name":"Eu sou grande e forte!"},{"lang":"de-DE","name":"Ich bin groß und stark!"},{"lang":"id-ID","name":"Aku besar dan kuat!"},{"lang":"fr-FR","name":"Je suis grand et fort !"}]},{"name":"You are small and weak!","isCorrect":false,"score":0,"translates":[{"lang":"ru-RU","name":"Ты маленький и слабый!"},{"lang":"vi-VN","name":"Ngươi nhỏ bé và yếu ớt!"},{"lang":"zh-CN","name":"你又小又弱！"},{"lang":"hi-IN","name":"तुम छोटे और कमजोर हो!"},{"lang":"th-TH","name":"เจ้าเล็กและอ่อนแอ!"},{"lang":"tr-TR","name":"Sen küçük ve zayıfsın!"},{"lang":"pt-BR","name":"Você é pequeno e fraco!"},{"lang":"de-DE","name":"Du bist klein und schwach!"},{"lang":"id-ID","name":"Kamu kecil dan lemah!"},{"lang":"fr-FR","name":"Tu es petit et faible !"}]}]},{"name":"You did it again!","actor":"Dot","dialogType":"Normal","translates":[{"lang":"ru-RU","name":"Ты снова это сделал!"},{"lang":"vi-VN","name":"Ngươi lại làm được rồi!"},{"lang":"zh-CN","name":"你又做到了！"},{"lang":"hi-IN","name":"तुमने फिर से कर दिखाया!"},{"lang":"th-TH","name":"เธอทำได้อีกแล้ว!"},{"lang":"tr-TR","name":"Yine başardın!"},{"lang":"pt-BR","name":"Você conseguiu de novo!"},{"lang":"de-DE","name":"Du hast es wieder geschafft!"},{"lang":"id-ID","name":"Kamu berhasil lagi!"},{"lang":"fr-FR","name":"Tu as réussi encore une fois !"}],"actions":[]}],"actors":[{"id":"Bun","name":"Bun","image":"/story/rb/npc/npc_bun.png","s":"u","isRight":false},{"id":"Dot","name":"Dot","image":"/story/rb/npc/npc_dot.png","s":"u"},{"id":"Bear","name":"Bear","image":"/story/rb/npc/npc_bear.png","s":"m"}]}