{
  "name": "Failed Attempt",
  "bg": "/img/story/bg/memory_field.png",
  "age": 0,
  "translations": [
    {
      "lang": "ru-RU",
      "name": "Неудачная попытка"
    }
  ],
  "items": [
    {
      "name": "Buzz, I see a broken memory.",
      "actor": "Lexi",
      "dialogType": "Normal",
      "translates": [
        {
          "lang": "ru-RU",
          "name": "Базз, я вижу сломанное воспоминание."
        }
      ]
    },
    {
      "name": "Yes, this one didn’t go well.",
      "actor": "Buzz",
      "dialogType": "Normal",
      "translates": [
        {
          "lang": "ru-RU",
          "name": "Да, тут что-то пошло не так."
        }
      ]
    },
    {
      "name": "Let’s fix it: I ___ the password, but it ___.",
      "actor": "Buzz",
      "dialogType": "Normal",
      "translates": [
        {
          "lang": "ru-RU",
          "name": "Давай исправим: Я ___ пароль, но он ___."
        }
      ],
      "actions": [
        {
          "name": "tried / failed",
          "isCorrect": true,
          "score": 1,
          "translates": [
            {
              "lang": "ru-RU",
              "name": "попробовала / не сработал"
            }
          ]
        },
        {
          "name": "try / fail",
          "isCorrect": false,
          "score": 0,
          "translates": [
            {
              "lang": "ru-RU",
              "name": "пробовать / не срабатывать"
            }
          ]
        },
        {
          "name": "trying / fails",
          "isCorrect": false,
          "score": 0,
          "translates": [
            {
              "lang": "ru-RU",
              "name": "пробую / не срабатывает"
            }
          ]
        }
      ]
    },
    {
      "name": "That’s it. Even mistakes are memories.",
      "actor": "Buzz",
      "dialogType": "Normal",
      "translates": [
        {
          "lang": "ru-RU",
          "name": "Вот так. Даже ошибки — это часть воспоминаний."
        }
      ]
    }
  ],
  "actors": [
    {
      "id": "Lexi",
      "name": "Lexi",
      "image": "/img/story/npc/npc_lexi.png",
      "s": "f"
    },
    {
      "id": "Buzz",
      "name": "Buzz",
      "image": "/img/story/npc/npc_buzz.png",
      "s": "n"
    }
  ]
}